[
    {
        "href": "http://www.sumo.or.jp/honbasho/topics/ko_torikumi15/detail?id=213",
        "movie": "http://www.sumo.or.jp//movie/kotorikumi/201509/september_01.mp4",
        "txt": "\u4e8c\u65e5\u76ee day \u767d\u9d6c \u5609\u98a8* (\u5f15\u304d\u843d\u3068\u3057) \u6a2a\u7db1\u767d\u9d6c\u304c\u307e\u3055\u304b\u306e\uff12\u9023\u6557\u3001\u5927\u817f\u56db\u982d\u7b4b\u8171\u708e\u306e\u70ba\u3001\uff13\u65e5\u76ee\u304b\u3089\u4f11\u5834\u3057\u3001\u6a2a\u7db1\u306b\u306a\u3063\u3066\u521d\u3081\u3066\uff14\uff19\u5834\u6240\u76ee\u3067\u4f11\u5834\u3001\u5e55\u5185\u9023\u7d9a\u4e8c\u6841\u52dd\u5229\u306f\uff15\uff11\u5834\u6240\u3067\u6b62\u307e\u3063\u305f\u3002"
    },
    {
        "href": "http://www.sumo.or.jp/honbasho/topics/ko_torikumi15/detail?id=214",
        "movie": "http://www.sumo.or.jp//movie/kotorikumi/201509/september_02.mp4",
        "txt": "\u4e09\u65e5\u76ee day \u5609\u98a8* \u9db4\u7adc (\u62bc\u3057\u51fa\u3057) \u5609\u98a8\u304c\u6a2a\u7db1\u9db4\u7adc\u3092\u7834\u308a\u4e8c\u65e5\u9023\u7d9a\u3067\u91d1\u661f\u3092\u7372\u5f97\u3057\u305f\u3002"
    },
    {
        "href": "http://www.sumo.or.jp/honbasho/topics/ko_torikumi15/detail?id=215",
        "movie": "http://www.sumo.or.jp//movie/kotorikumi/201509/september_03.mp4",
        "txt": "\u5341\u4e00\u65e5\u76ee day \u7167\u30ce\u5bcc\u58eb* \u7434\u5968\u83ca (\u5bc4\u308a\u5012\u3057) \u5927\u95a2\u7167\u30ce\u5bcc\u58eb\u304c\u7121\u50b7\u306e\uff11\uff11\u9023\u52dd\u3001\u5e74\u9593\u52dd\u5229\u306f\uff15\uff15\u52dd\u3068\u306a\u308a\u767d\u9d6c\u3092\u629c\u3044\u3066\u30c8\u30c3\u30d7\u3068\u306a\u308b\u3002"
    },
    {
        "href": "http://www.sumo.or.jp/honbasho/topics/ko_torikumi15/detail?id=216",
        "movie": "http://www.sumo.or.jp//movie/kotorikumi/201509/september_04.mp4",
        "txt": "\u5341\u4e00\u65e5\u76ee day \u6803\u714c\u5c71 \u9db4\u7adc* (\u53e9\u304d\u8fbc\u307f) \u5341\u65e5\u76ee\u3001\u5999\u7fa9\u9f8d\u306b\u6557\u308c\uff12\u6557\u3068\u306a\u308a\u5f8c\u306e\u7121\u3044\u6a2a\u7db1\u9db4\u7adc\u306f\u53e9\u304d\u8fbc\u307f\u3067\u6803\u714c\u5c71\u3092\u7834\u308b\u3002"
    },
    {
        "href": "http://www.sumo.or.jp/honbasho/topics/ko_torikumi15/detail?id=217",
        "movie": "http://www.sumo.or.jp//movie/kotorikumi/201509/september_05.mp4",
        "txt": "\u5341\u4e8c\u65e5\u76ee day \u7167\u30ce\u5bcc\u58eb \u6803\u714c\u5c71* (\u5bc4\u308a\u5207\u308a) \u5168\u52dd\u306e\u7167\u30ce\u5bcc\u58eb\u306b\u571f\u3001\uff11\u6557\u3067\u7167\u30ce\u5bcc\u58eb\u3001\uff12\u6557\u306f\u9db4\u7adc\u3001\u52e2\u3001\uff13\u6557\u306f\u7a00\u52e2\u306e\u91cc\u3001\u8c4a\u30ce\u5cf6\u3068\u306a\u308b\u3002"
    },
    {
        "href": "http://www.sumo.or.jp/honbasho/topics/ko_torikumi15/detail?id=218",
        "movie": "http://www.sumo.or.jp//movie/kotorikumi/201509/september_06.mp4",
        "txt": "\u5341\u4e09\u65e5\u76ee day \u6803\u30ce\u5fc3* \u52e2 (\u5bc4\u308a\u5207\u308a) \u52e2\u304c\u6803\u30ce\u5fc3\u306b\u6557\u308c\uff13\u6557\u3068\u306a\u308b\u3002"
    },
    {
        "href": "http://www.sumo.or.jp/honbasho/topics/ko_torikumi15/detail?id=219",
        "movie": "http://www.sumo.or.jp//movie/kotorikumi/201509/september_07.mp4",
        "txt": "\u5341\u4e09\u65e5\u76ee day \u7167\u30ce\u5bcc\u58eb \u7a00\u52e2\u306e\u91cc* (\u5bc4\u308a\u5012\u3057) \u7167\u30ce\u5bcc\u58eb\u304c\u6557\u308c\uff12\u6557\u3068\u306a\u308a\u3001\u7a00\u52e2\u306e\u91cc\u306f\uff13\u6557\u3092\u30ad\u30fc\u30d7\u3059\u308b\u3002"
    },
    {
        "href": "http://www.sumo.or.jp/honbasho/topics/ko_torikumi15/detail?id=220",
        "movie": "http://www.sumo.or.jp//movie/kotorikumi/201509/september_08.mp4",
        "txt": "\u5341\u4e09\u65e5\u76ee day \u8c6a\u6804\u9053 \u9db4\u7adc* (\u5bc4\u308a\u5207\u308a) \u6a2a\u7db1\u9db4\u7adc\u304c\u8c6a\u6804\u9053\u3092\u4e0b\u3057\u3001\uff12\u6557\u306f\u9db4\u7adc\u3068\u7167\u30ce\u5bcc\u58eb\u3001\uff13\u6557\u3067\u7a00\u52e2\u306e\u91cc\u3068\u52e2\u3068\u306a\u308b\u3002"
    },
    {
        "href": "http://www.sumo.or.jp/honbasho/topics/ko_torikumi15/detail?id=221",
        "movie": "http://www.sumo.or.jp//movie/kotorikumi/201509/september_09.mp4",
        "txt": "\u5341\u56db\u65e5\u76ee day \u52e2 \u7434\u5968\u83ca* (\u62bc\u3057\u51fa\u3057) \uff13\u6557\u306e\u52e2\u304c\u6557\u308c\u3001\uff14\u6557\u3068\u306a\u308a\u512a\u52dd\u4e89\u3044\u304b\u3089\u8131\u843d\u3059\u308b\u3002"
    },
    {
        "href": "http://www.sumo.or.jp/honbasho/topics/ko_torikumi15/detail?id=222",
        "movie": "http://www.sumo.or.jp//movie/kotorikumi/201509/september_10.mp4",
        "txt": "\u5341\u56db\u65e5\u76ee day \u7167\u30ce\u5bcc\u58eb \u8c6a\u6804\u9053* (\u5bc4\u308a\u5207\u308a) \uff12\u6557\u306e\u7167\u30ce\u5bcc\u58eb\u304c\u8c6a\u6804\u9053\u306b\u6557\u308c\u3001\u5343\u79cb\u697d\u306b\u672c\u5272\u308a\u3067\u52dd\u3061\u6c7a\u5b9a\u6226\u306b\u6301\u3061\u8fbc\u307f\u305f\u3044\u3002"
    },
    {
        "href": "http://www.sumo.or.jp/honbasho/topics/ko_torikumi15/detail?id=223",
        "movie": "http://www.sumo.or.jp//movie/kotorikumi/201509/september_11.mp4",
        "txt": "\u5341\u56db\u65e5\u76ee day \u7a00\u52e2\u306e\u91cc \u9db4\u7adc* (\u5bc4\u308a\u5012\u3057) \u9db4\u7adc\u306f\u7a00\u52e2\u306e\u91cc\u3092\u7834\u308a\uff12\u6557\u3092\u5b88\u308b\u3002\u5343\u79cb\u697d\u306b\u672c\u5272\u308a\u3067\u52dd\u3061\u512a\u52dd\u3092\u6c7a\u3081\u305f\u3044\u3002"
    },
    {
        "href": "http://www.sumo.or.jp/honbasho/topics/ko_torikumi15/detail?id=224",
        "movie": "http://www.sumo.or.jp//movie/kotorikumi/201509/september_12.mp4",
        "txt": "\u5343\u79cb\u697d day \u52e2* \u963f\u5922\u9732 (\u5bc4\u308a\u5207\u308a) \u52e2\u304c\u963f\u5922\u9732\u3092\u7834\u308a\uff11\uff11\u52dd\u3092\u6319\u3052\u3001\uff13\u5ea6\u76ee\u306e\u6562\u95d8\u8cde\u3068\u306a\u308b\u3002"
    },
    {
        "href": "http://www.sumo.or.jp/honbasho/topics/ko_torikumi15/detail?id=225",
        "movie": "http://www.sumo.or.jp//movie/kotorikumi/201509/september_13.mp4",
        "txt": "\u5343\u79cb\u697d day \u6803\u30ce\u5fc3* \u8c4a\u30ce\u5cf6 (\u5bc4\u308a\u5207\u308a) \u6803\u30ce\u5fc3\u304c\u5343\u79cb\u697d\uff11\uff10\u52dd\u3092\u6319\u3052\uff15\u5ea6\u76ee\u306e\u6562\u95d8\u8cde\u306b\u9078\u3070\u308c\u305f\u3002"
    },
    {
        "href": "http://www.sumo.or.jp/honbasho/topics/ko_torikumi15/detail?id=226",
        "movie": "http://www.sumo.or.jp//movie/kotorikumi/201509/september_14.mp4",
        "txt": "\u5343\u79cb\u697d day \u7167\u30ce\u5bcc\u58eb* \u9db4\u7adc (\u5bc4\u308a\u5207\u308a) \u7167\u30ce\u5bcc\u58eb\u304c\u52dd\u3063\u3066\u76f8\u661f\u3068\u306a\u308a\u6c7a\u5b9a\u6226\u3078\u3002"
    },
    {
        "href": "http://www.sumo.or.jp/honbasho/topics/ko_torikumi15/detail?id=227",
        "movie": "http://www.sumo.or.jp//movie/kotorikumi/201509/september_15.mp4",
        "txt": "\u5343\u79cb\u697d day \u9db4\u7adc* \u7167\u30ce\u5bcc\u58eb (\u4e0a\u624b\u51fa\u3057\u6295\u3052) (\u512a\u52dd\u6c7a\u5b9a\u6226)"
    }
]
